LICENSE.txt
MANIFEST.in
README.rst
setup.py
mode_behave.egg-info/PKG-INFO
mode_behave.egg-info/SOURCES.txt
mode_behave.egg-info/dependency_links.txt
mode_behave.egg-info/not-zip-safe
mode_behave.egg-info/requires.txt
mode_behave.egg-info/top_level.txt
mode_behave_public/__init__.py
mode_behave_public/config.py
mode_behave_public/core.py
mode_behave_public/estimation.py
mode_behave_public/post_analysis.py
mode_behave_public/simulation.py
mode_behave_public/Deployments/example_estimation.py
mode_behave_public/InputData/example_data.csv
mode_behave_public/ModelParam/asc_offset_hh_cars.csv
mode_behave_public/ModelParam/initial_point_artificial_data.csv
mode_behave_public/ModelParam/initial_point_car_ownership.csv
mode_behave_public/ModelParam/initial_point_mode.csv
mode_behave_public/ModelParam/speed_parameters.csv
mode_behave_public/Visualizations/forecast_clustering.png
mode_behave_public/Visualizations/forecast_sensitivity.png
test/test_estimation.py
test/test_simulation.py