Metadata-Version: 2.1
Name: mode-behave
Version: 1.1.2
Summary: Estimation and simulation of discrete choice models
Home-page: https://github.com/julianreul/mode_behave
Author: Julian Reul
Author-email: j.reul@fz-juelich.de
License: MIT
License-File: LICENSE.txt
